caom2utils/__init__.py
caom2utils/blueprints.py
caom2utils/caom2blueprint.py
caom2utils/caomvalidator.py
caom2utils/data_util.py
caom2utils/legacy.py
caom2utils/parsers.py
caom2utils/polygonvalidator.py
caom2utils/version.py
caom2utils/wcs_parsers.py
caom2utils/wcs_util.py
caom2utils/wcsvalidator.py
caom2utils/tests/__init__.py
caom2utils/tests/conftest.py
caom2utils/tests/test_caomvalidator.py
caom2utils/tests/test_collections.py
caom2utils/tests/test_convert_from_java.py
caom2utils/tests/test_custom_axis_util.py
caom2utils/tests/test_data_util.py
caom2utils/tests/test_fits2caom2.py
caom2utils/tests/test_obs_blueprint.py
caom2utils/tests/test_polygonvalidator.py
caom2utils/tests/test_si_uris.py
caom2utils/tests/test_wcsvalidator.py
caom2utils/tests/data/4axes.fits
caom2utils/tests/data/4axes.override
caom2utils/tests/data/4axes_obs.fits
caom2utils/tests/data/SampleComposite-CAOM-2.3.xml
caom2utils/tests/data/bad_product_id.txt
caom2utils/tests/data/bad_product_id.xml
caom2utils/tests/data/edge_case.blueprint
caom2utils/tests/data/fits2caom2.config
caom2utils/tests/data/help.txt
caom2utils/tests/data/java.config
caom2utils/tests/data/missing_observation_help.txt
caom2utils/tests/data/missing_positional_argument_help.txt
caom2utils/tests/data/missing_product_id.txt
caom2utils/tests/data/nonconformant.py
caom2utils/tests/data/test.override
caom2utils/tests/data/test_plugin.py
caom2utils/tests/data/test_plugin_class.py
caom2utils/tests/data/text.override
caom2utils/tests/data/time_axes.fits
caom2utils/tests/data/too_few_arguments_help.txt
caom2utils-1.7.3.dist-info/licenses/LICENSE
caom2utils-1.7.3.dist-info/METADATA
caom2utils-1.7.3.dist-info/WHEEL
caom2utils-1.7.3.dist-info/entry_points.txt
caom2utils-1.7.3.dist-info/top_level.txt
caom2utils-1.7.3.dist-info/RECORD
