Metadata-Version: 2.4
Name: caom2utils
Version: 1.7.3
Summary: CAOM-2.4 utils
Home-page: https://www.cadc-ccda.hia-iha.nrc-cnrc.gc.ca/caom2
Author: Canadian Astronomy Data Centre
Author-email: cadc@nrc-cnrc.gc.ca
License: AGPLv3
Classifier: Natural Language :: English
Classifier: License :: OSI Approved :: GNU Affero General Public License v3
Classifier: Programming Language :: Python
Classifier: Programming Language :: Python :: 3
Requires-Python: >=3.8, <4
License-File: LICENSE
Requires-Dist: cadcdata>=2.5.2
Requires-Dist: caom2>=2.6
Requires-Dist: astropy>=2.0
Requires-Dist: spherical-geometry>=1.2.11
Requires-Dist: vos>=3.1.1
Provides-Extra: h5
Requires-Dist: h5py; extra == "h5"
Provides-Extra: test
Requires-Dist: pytest>=6.2; extra == "test"
Requires-Dist: pytest-cov>=2.12; extra == "test"
Requires-Dist: flake8>=3.9; extra == "test"
Requires-Dist: xml-compare>=1.0.5; extra == "test"
Dynamic: author
Dynamic: author-email
Dynamic: classifier
Dynamic: description
Dynamic: home-page
Dynamic: license
Dynamic: license-file
Dynamic: requires-python
Dynamic: summary
